ocx_xml/__init__.py
ocx_xml/xml_element.py
ocx_xml/xml_parser.py
ocx_xml-0.1.0.dist-info/LICENSE
ocx_xml-0.1.0.dist-info/WHEEL
ocx_xml-0.1.0.dist-info/METADATA
ocx_xml-0.1.0.dist-info/RECORD
